[
  {
    "id": "rec-sparkle-1",
    "djId": "1",
    "djName": "DJ Sparkle",
    "title": "Midnight Drive",
    "album": "City Lights EP",
    "year": 2023,
    "type": "EP",
    "artworkUrl": "techno-ep-artwork.png",
    "aiHint": "abstract cityscape",
    "genre": "Techno",
    "fanScore": 8.5,
    "totalPlays": 120500,
    "description": "A driving techno track for late nights.",
    "addedDate": "2023-07-15T00:00:00.000Z",
    "artwork": "https://source.unsplash.com/featured/?abstract,cityscape"
  },
  {
    "id": "rec-sparkle-2",
    "djId": "1",
    "djName": "DJ Sparkle",
    "title": "Rooftop Groove",
    "year": 2024,
    "type": "Single",
    "artworkUrl": "house-single-artwork.png",
    "aiHint": "neon lights party",
    "genre": "House",
    "fanScore": 9.1,
    "totalPlays": 75300,
    "description": "Uplifting house vibes.",
    "addedDate": "2024-01-20T00:00:00.000Z",
    "artwork": "https://source.unsplash.com/featured/?neon,lights,party"
  },
  {
    "id": "rec-groove-1",
    "djId": "2",
    "djName": "Groove Master G",
    "title": "Funkadelic Flow Vol. 1",
    "year": 2022,
    "type": "Mix",
    "artworkUrl": "funk-mix-artwork.png",
    "aiHint": "vinyl records funk",
    "genre": "Funk",
    "fanScore": 7.8,
    "totalPlays": 250000,
    "description": "An hour of pure funk.",
    "addedDate": "2022-11-10T00:00:00.000Z",
    "artwork": "https://source.unsplash.com/featured/?vinyl,records,funk"
  },
  {
    "id": "rec-beatrix-1",
    "djId": "3",
    "djName": "Beatrix Kiddo",
    "title": "Future Soundscapes",
    "album": "Digital Dreams",
    "year": 2024,
    "type": "Album",
    "artworkUrl": "electronic-album-artwork.png",
    "aiHint": "futuristic audio waves",
    "genre": "Electronic",
    "fanScore": 9.5,
    "totalPlays": 95000,
    "description": "A journey through ethereal electronic soundscapes.",
    "addedDate": "2024-03-01T00:00:00.000Z",
    "artwork": "https://source.unsplash.com/featured/?futuristic,audio,waves"
  },
  {
    "id": "rec-beatrix-2",
    "djId": "3",
    "djName": "Beatrix Kiddo",
    "title": "Tech Pulse",
    "year": 2023,
    "type": "Single",
    "artworkUrl": "techno-single-artwork.png",
    "aiHint": "circuit board music",
    "genre": "Techno",
    "fanScore": 8.2,
    "totalPlays": 60000,
    "description": "Minimalistic and powerful techno.",
    "addedDate": "2023-05-25T00:00:00.000Z",
    "artwork": "https://source.unsplash.com/featured/?circuit,board,music"
  },
  {
    "id": "rec-vinyl-1",
    "djId": "4",
    "djName": "Vinyl Villain",
    "title": "Indie Anthem",
    "year": 2023,
    "type": "Single",
    "artworkUrl": "indie-rock-single-artwork.png",
    "aiHint": "guitar silhouette concert",
    "genre": "Indie Rock",
    "fanScore": 8.8,
    "addedDate": "2023-09-05T00:00:00.000Z",
    "totalPlays": 150000,
    "description": "An anthemic indie rock track with soaring vocals and driving guitars.",
    "artwork": "https://source.unsplash.com/featured/?guitar,silhouette,concert"
  },
  {
    "id": "rec-echo-1",
    "djId": "5",
    "djName": "DJ Echo",
    "title": "Lo-Fi Dreams",
    "album": "Chill Vibes Only",
    "year": 2022,
    "type": "Album",
    "artworkUrl": "lofi-album-artwork.png",
    "aiHint": "sunset window lofi",
    "genre": "Lo-Fi",
    "fanScore": 9.5,
    "addedDate": "2022-08-01T00:00:00.000Z",
    "totalPlays": 300000,
    "description": "The perfect Lo-Fi album for studying, relaxing, or quiet contemplation.",
    "artwork": "https://source.unsplash.com/featured/?sunset,window,lofi"
  },
  {
    "id": "rec-default-generic",
    "djId": "unknown",
    "djName": "Various Artist",
    "title": "Generic Track One",
    "year": 2022,
    "type": "Single",
    "artworkUrl": "electronic-music-artwork.png",
    "aiHint": "sound wave abstract",
    "genre": "Electronic",
    "fanScore": 6.5,
    "addedDate": "2022-01-01T00:00:00.000Z",
    "totalPlays": 10000,
    "description": "A generic electronic track showcasing various synth sounds and rhythmic patterns.",
    "artwork": "https://source.unsplash.com/featured/?sound,wave,abstract"
  }
]
